{
"type": "FeatureCollection",
"name": "best_candidate_per_tract",
"crs": { "type": "name", "properties": { "name": "urn:ogc:def:crs:OGC:1.3:CRS84" } },
"features": [
{ "type": "Feature", "properties": { "cand_id": 120, "TRACTCE": "011001", "d_t_m": 14.371728921498363, "d_b_m": 5.1220653242796139, "St": 0.95209757026167208, "Sb": 0.98292978225240124, "St_norm": 0.92198545704815882, "Sb_norm": 0.93263585153910233, "SS": 0.92731065429363058, "market_share": 23447304.950249966 }, "geometry": { "type": "Point", "coordinates": [ -122.421248781, 37.793709399 ] } },
{ "type": "Feature", "properties": { "cand_id": 26, "TRACTCE": "011101", "d_t_m": 38.731735154323864, "d_b_m": 23.653835764722043, "St": 0.87089754948558706, "Sb": 0.9211572141175931, "St_norm": 0.74494012472815241, "Sb_norm": 0.27593909183316317, "SS": 0.51043960828065782, "market_share": 29900630.291589703 }, "geometry": { "type": "Point", "coordinates": [ -122.417418428, 37.791456679 ] } },
{ "type": "Feature", "properties": { "cand_id": 94, "TRACTCE": "011102", "d_t_m": 46.328791446632245, "d_b_m": 26.840546394499626, "St": 0.84557402851122587, "Sb": 0.91053484535166795, "St_norm": 0.72952842652807004, "Sb_norm": 0.24235572828078425, "SS": 0.48594207740442713, "market_share": 130980399.79780236 }, "geometry": { "type": "Point", "coordinates": [ -122.419007771999986, 37.790300299 ] } },
{ "type": "Feature", "properties": { "cand_id": 457, "TRACTCE": "012001", "d_t_m": 86.162205660105386, "d_b_m": 18.930279260889986, "St": 0.71279598113298215, "Sb": 0.93690240246370005, "St_norm": 0.30305213429101185, "Sb_norm": 0.36992767022916445, "SS": 0.33648990226008813, "market_share": 31087239.929085601 }, "geometry": { "type": "Point", "coordinates": [ -122.41939581, 37.788381760999989 ] } },
{ "type": "Feature", "properties": { "cand_id": 761, "TRACTCE": "012002", "d_t_m": 295.00220319527421, "d_b_m": 8.8052559729182764, "St": 0.016662656015752651, "Sb": 0.97065248009027227, "St_norm": 0.016867054575881984, "Sb_norm": 0.87104232689184435, "SS": 0.44395469073386318, "market_share": 38607847.508320257 }, "geometry": { "type": "Point", "coordinates": [ -122.416664587, 37.787720247 ] } },
{ "type": "Feature", "properties": { "cand_id": 92, "TRACTCE": "026001", "d_t_m": 116.4340253091715, "d_b_m": 26.601516676813389, "St": 0.61188991563609507, "Sb": 0.91133161107728866, "St_norm": 0.45103127178857644, "Sb_norm": 0.63455735196739038, "SS": 0.54279431187798344, "market_share": 107045493.51718399 }, "geometry": { "type": "Point", "coordinates": [ -122.431783475, 37.724299845 ] } },
{ "type": "Feature", "properties": { "cand_id": 251, "TRACTCE": "026100", "d_t_m": 162.8500123826739, "d_b_m": 21.450576320301426, "St": 0.45716995872442034, "Sb": 0.92850141226566185, "St_norm": 0.46215966513461809, "Sb_norm": 0.79435647969259715, "SS": 0.62825807241360765, "market_share": 24474655.390796885 }, "geometry": { "type": "Point", "coordinates": [ -122.446147988, 37.71857058 ] } },
{ "type": "Feature", "properties": { "cand_id": 599, "TRACTCE": "032802", "d_t_m": 159.18791158453254, "d_b_m": 22.041275308742165, "St": 0.46937696138489154, "Sb": 0.92653241563752597, "St_norm": 0.53157801149835571, "Sb_norm": 0.9444006868701692, "SS": 0.7379893491842624, "market_share": 29099724.055566702 }, "geometry": { "type": "Point", "coordinates": [ -122.478481803, 37.753216849 ] } },
{ "type": "Feature", "properties": { "cand_id": 159, "TRACTCE": "032902", "d_t_m": 143.33848314712804, "d_b_m": 23.987524993149304, "St": 0.52220838950957316, "Sb": 0.92004491668950228, "St_norm": 0.53713400092607344, "Sb_norm": 0.67168827119094521, "SS": 0.60441113605850938, "market_share": 44734975.614479594 }, "geometry": { "type": "Point", "coordinates": [ -122.490536545999987, 37.754556803 ] } },
{ "type": "Feature", "properties": { "cand_id": 153, "TRACTCE": "042700", "d_t_m": 26.284539065271943, "d_b_m": 18.203214159096028, "St": 0.91238820311576019, "Sb": 0.93932595280301312, "St_norm": 0.90633785705293335, "Sb_norm": 0.73693585860232202, "SS": 0.82163685782762763, "market_share": 105913775.54517283 }, "geometry": { "type": "Point", "coordinates": [ -122.485553764000016, 37.783912697 ] } }
]
}
